{
  "forge_marker": 1,
  "defaults": {
    "model": "cross",
    "uvlock": true
  },
  "variants": {
    "level": {
      "0": { "textures": { "cross": "atlantis:blocks/underwater_flower"}},
      "1": { "textures": { "cross": "atlantis:blocks/underwater_flower"}},
      "2": { "textures": { "cross": "atlantis:blocks/underwater_flower"}},
      "3": { "textures": { "cross": "atlantis:blocks/underwater_flower"}},
      "4": { "textures": { "cross": "atlantis:blocks/underwater_flower"}},
      "5": { "textures": { "cross": "atlantis:blocks/underwater_flower"}},
      "6": { "textures": { "cross": "atlantis:blocks/underwater_flower"}},
      "7": { "textures": { "cross": "atlantis:blocks/underwater_flower"}},
      "8": { "textures": { "cross": "atlantis:blocks/underwater_flower"}},
      "9": { "textures": { "cross": "atlantis:blocks/underwater_flower"}},
      "10": { "textures": { "cross": "atlantis:blocks/underwater_flower"}},
      "11": { "textures": { "cross": "atlantis:blocks/underwater_flower"}},
      "12": { "textures": { "cross": "atlantis:blocks/underwater_flower"}},
      "13": { "textures": { "cross": "atlantis:blocks/underwater_flower"}},
      "14": { "textures": { "cross": "atlantis:blocks/underwater_flower"}},
      "15": { "textures": { "cross": "atlantis:blocks/underwater_flower"}}
    }
  }
}